{
    "parameters": [
        {
            "definition": "Number of warehouse candidates",
            "symbol": "n_suppliers",
            "shape": []
        },
        {
            "definition": "Number of stores",
            "symbol": "n_stores",
            "shape": []
        },
        {
            "definition": "Cost of opening a warehouse",
            "symbol": "building_cost",
            "shape": []
        },
        {
            "definition": "Array containing the capacity of each warehouse",
            "symbol": "capacity",
            "shape": [
                "n_suppliers"
            ]
        },
        {
            "definition": "Cost matrix where each element represents the cost of a store being supplied by a warehouse",
            "symbol": "cost_matrix",
            "shape": [
                "n_stores",
                "n_suppliers"
            ]
        }
    ],
    "output": [
        {
            "definition": "Total cost which includes maintenance and supply costs",
            "symbol": "tot",
            "shape": []
        },
        {
            "definition": "Array indicating which warehouse supplies each store",
            "symbol": "supplier",
            "shape": [
                "n_stores"
            ]
        },
        {
            "definition": "Array containing the cost for each store",
            "symbol": "cost",
            "shape": [
                "n_stores"
            ]
        },
        {
            "definition": "Array indicating if each warehouse is open (boolean)",
            "symbol": "open",
            "shape": [
                "n_suppliers"
            ]
        }
    ],
    "description": "In the Warehouse Location problem (WLP), a company aims to open warehouses at candidate locations to supply its stores. Each warehouse has a maintenance cost and specific capacity. Each store must be supplied by exactly one warehouse, with supply costs varying per warehouse. The goal is to minimize the sum of maintenance and supply costs by determining which warehouses to open and assigning them to supply stores.",
    "metadata": {
        "name": "Warehouse Location Problem",
        "domain": "Transportation and Logistics",
        "objective": "minimization",
        "source": "CSPLib",
        "constraints": [
            "sum",
            "bool2int",
            "forall",
            "exists",
            "<->",
            "<=",
            "="
        ],
        "identifier": "CSPLib_34"
    }
}